pyenvelope.py
setup.py
pyenvelope.egg-info/PKG-INFO
pyenvelope.egg-info/SOURCES.txt
pyenvelope.egg-info/dependency_links.txt
pyenvelope.egg-info/requires.txt
pyenvelope.egg-info/top_level.txt