Metadata-Version: 1.0
Name: pyenvelope
Version: 0.1
Summary: Minimum bounding rectangle calculation
Home-page: https://github.com/kaygorodov/pyenvelope
Author: Andrey Kaygorodov
Author-email: andreykaygorodov@gmail.com
License: UNKNOWN
Platform: UNKNOWN
